statds/__init__.py
statds/app.py
statds/homoscedasticity.py
statds/no_parametrics.py
statds/normality.py
statds/parametrics.py
statds/stats.py
statds/utils.py
statds/assets/app/README.md
statds/assets/app/sample_dataset.csv
statds/assets/app/style.css
statds/assets/images/amoya.png
statds/assets/images/i82luesc.png
statds/assets/images/jmluna.png
statds/assets/images/logo-StaTDS-without-background.png
statds/assets/images/logo-StaTDS.png
statds/assets/images/logo-github.png
statds/assets/images/logo-kdislab.png
statds/assets/images/logo-python.png
statds/assets/images/logo-send-email.png
statds/assets/images/sventura.png
statds/assets/statistical_tables/CV_Minimum_r.csv
statds/assets/statistical_tables/CV_Wilcoxon.csv
statds/assets/statistical_tables/CV_q_table.csv
statds/assets/statistical_tables/chi_table.csv
statds/assets/statistical_tables/f_table.csv
statds/assets/statistical_tables/nemenyi_table.csv
statds/assets/statistical_tables/normal_table.csv
statds/assets/statistical_tables/shapiro_table.csv
statds/assets/statistical_tables/shapiro_weights.csv
statds/assets/statistical_tables/t_table.csv
statds-1.1.7.dist-info/LICENSE
statds-1.1.7.dist-info/METADATA
statds-1.1.7.dist-info/WHEEL
statds-1.1.7.dist-info/top_level.txt
statds-1.1.7.dist-info/RECORD
