Metadata-Version: 2.1
Name: statds
Version: 1.1.7
Summary: Library for statistical testing and comparison of algorithm results
Home-page: https://github.com/kdis-lab/StaTDS
Author: Christian Luna Escudero, Antonio R. Moya Martín-Castaño, José María Luna Ariza, Sebastián Ventura Soto
Author-email: i82luesc@uco.es, sventura@uco.es
Keywords: Test Statistical,Parametrics Tests,No Parametrics Tests,Comparare Algorithms Results,Post-hoc Tests
License-File: LICENSE
Requires-Dist: pandas >=2.0
Requires-Dist: numpy >=1.20
Requires-Dist: matplotlib >=3.7
Provides-Extra: full-app
Requires-Dist: dash ==2.16.1 ; extra == 'full-app'
Requires-Dist: dash-bootstrap-components ==1.4.2 ; extra == 'full-app'
Requires-Dist: dash-daq ==0.5.0 ; extra == 'full-app'
Requires-Dist: dash-ag-grid ==2.3.0 ; extra == 'full-app'
Requires-Dist: fpdf2 ==2.7.5 ; extra == 'full-app'
Provides-Extra: pdf
Requires-Dist: fpdf2 ==2.7.5 ; extra == 'pdf'
